allyanonimiser/__init__.py
allyanonimiser/allyanonimiser.py
allyanonimiser/dataframe_processor.py
allyanonimiser/enhanced_analyzer.py
allyanonimiser/enhanced_anonymizer.py
allyanonimiser/pattern_manager.py
allyanonimiser/pattern_registry.py
allyanonimiser/reporting.py
allyanonimiser/stream_processor.py
allyanonimiser/validators.py
allyanonimiser/generators/__init__.py
allyanonimiser/generators/au_synthetic_data.py
allyanonimiser/generators/dataset_publisher.py
allyanonimiser/generators/llm_augmenter.py
allyanonimiser/insurance/__init__.py
allyanonimiser/insurance/claim_notes_analyzer.py
allyanonimiser/insurance/email_analyzer.py
allyanonimiser/insurance/medical_report_analyzer.py
allyanonimiser/patterns/__init__.py
allyanonimiser/patterns/au_patterns.py
allyanonimiser/patterns/general_patterns.py
allyanonimiser/patterns/insurance_patterns.py
allyanonimiser/tests/__init__.py
allyanonimiser/tests/conftest.py
allyanonimiser/tests/test_analyzer.py
allyanonimiser/tests/test_anonymizer.py
allyanonimiser/tests/test_generators.py
allyanonimiser/tests/test_main_interface.py
allyanonimiser/utils/__init__.py
allyanonimiser/utils/long_text_processor.py
allyanonimiser/utils/presidio_helpers.py
allyanonimiser/utils/settings_manager.py
allyanonimiser/utils/spacy_helpers.py
allyanonimiser/utils/text_preprocessor.py
generators/__init__.py
generators/au_synthetic_data.py
generators/dataset_publisher.py
generators/llm_augmenter.py
insurance/__init__.py
insurance/claim_notes_analyzer.py
insurance/email_analyzer.py
insurance/medical_report_analyzer.py
patterns/__init__.py
patterns/au_patterns.py
patterns/general_patterns.py
patterns/insurance_patterns.py
tests/__init__.py
tests/conftest.py
tests/run_functional_tests.py
tests/run_package_tests.py
tests/run_tests.py
tests/test_age_bracketing.py
tests/test_analyzer.py
tests/test_anonymizer.py
tests/test_circular_import_fix.py
tests/test_complex_csv_import.py
tests/test_config_export.py
tests/test_csv_import.py
allyanonimiser-2.1.0.dist-info/LICENSE
allyanonimiser-2.1.0.dist-info/METADATA
allyanonimiser-2.1.0.dist-info/WHEEL
allyanonimiser-2.1.0.dist-info/top_level.txt
allyanonimiser-2.1.0.dist-info/RECORD
