Metadata-Version: 2.2
Name: allyanonimiser
Version: 2.1.0
Summary: Australian-focused PII detection and anonymization for the insurance industry
Home-page: https://github.com/srepho/Allyanonimiser
Author: Stephen Oates
Author-email: Stephen Oates <stephen.j.a.oates@gmail.com>
License: MIT License
Project-URL: Homepage, https://github.com/srepho/Allyanonimiser
Project-URL: Bug Tracker, https://github.com/srepho/Allyanonimiser/issues
Project-URL: Documentation, https://github.com/srepho/Allyanonimiser#readme
Keywords: pii,anonymization,privacy,insurance,australia
Classifier: Programming Language :: Python :: 3
Classifier: Programming Language :: Python :: 3.10
Classifier: Programming Language :: Python :: 3.11
Classifier: Programming Language :: Python :: 3.12
Classifier: License :: OSI Approved :: MIT License
Classifier: Operating System :: OS Independent
Classifier: Topic :: Security
Classifier: Topic :: Text Processing
Requires-Python: >=3.10
License-File: LICENSE
Requires-Dist: spacy>=3.5.0
Requires-Dist: presidio-analyzer>=2.2.0
Requires-Dist: presidio-anonymizer>=2.2.0
Requires-Dist: pandas>=1.0.0
Requires-Dist: tqdm>=4.64.0
Provides-Extra: dev
Requires-Dist: pytest>=7.0.0; extra == "dev"
Requires-Dist: pytest-cov>=4.0.0; extra == "dev"
Requires-Dist: black>=22.0.0; extra == "dev"
Requires-Dist: isort>=5.0.0; extra == "dev"
Requires-Dist: flake8>=5.0.0; extra == "dev"
Requires-Dist: mypy>=0.9.0; extra == "dev"
Provides-Extra: llm
Requires-Dist: openai>=0.27.0; extra == "llm"
Requires-Dist: anthropic>=0.3.0; extra == "llm"
Provides-Extra: stream
Requires-Dist: polars>=0.20.0; extra == "stream"
Requires-Dist: pyarrow>=14.0.0; extra == "stream"
Dynamic: author
Dynamic: home-page
Dynamic: requires-python
